{
  "header": {
    "recordLength": 3714
  },
  "payload": {
    "genericRecord": {
      "recordType": "OCSChargingRecord",
      "recordElements": {
        "prevMeName": "ig-charging-68775f8668-n5gf2",
        "recordId": "20250908193824_ad6f8608-e5ac-493b-b471-b7b619a54fef",
        "generationTimestamp": "08/09/2025 19:38:24+03:00",
        "singleCDREnabled": "true",
        "sessionId": "0000001706;x5v2c7-0000002667.0000000498;",
        "serviceContextId": "32260@3gpp.org",
        "requestType": "TERMINATION_REQUEST",
        "singleCDRTriggerEvent": "TERMINATION_REQUEST",
        "sessionSequenceNumber": "1",
        "deviceTimeZone": "1800",
        "sessionStartTime": "08/09/2025 19:38:06+03:00",
        "callAnswerTime": "08/09/2025 19:38:24+03:00",
        "callEndTime": "08/09/2025 19:38:24+03:00",
        "dayOfWeek": "Monday",
        "originHost": "ss7dh2-0-dh_20_6-P0-3.ss7dh2-0.spscentosslee",
        "deviceId": "D_10435081",
        "deviceName": "D_10435081",
        "deviceOwner": "U_10435081",
        "deviceOwnerName": "U_10435081",
        "ocsHost": "mdc1labnccs01-oam.safaricomlab.net",
        "deviceState": "ACTIVE",
        "devicePartitionId": "1",
        "deviceSiteId": "1",
        "imsChargingIdentifier": "401f701d0f4d23",
        "roamingIndicator": "HOME",
        "totalRoundedDuration": "0",
        "MCCMNC": "63602",
        "DATAOOBFLAG": "FALSE",
        "RoamingStatus": "Home",
        "PeakTime": "Peak",
        "DestinationType": "Ethiopia_Offnet",
        "DestinationCountry": "Ethiopia",
        "Rating_Origination_Location": "Ethiopia",
        "causeForRecClosing": "1",
        "rATType": "6",
        "resultCode": "2001",
        "roleOfNode": "Originating-Role",
        "origUserLocationInfo": "6360215b2957b",
        "userLocationInformation": "6360215b2957b",
        "callingPartyAddress": "251700900449",
        "mediaName": "audio",
        "calledPartyAddress": "251905197676",
        "callDuration": "0",
        "recordOpeningTime": "08/09/2025 19:38:06+03:00",
        "recordClosureTime": "08/09/2025 19:38:24+03:00",
        "duration": "18",
        "recordSequenceNumber": "1",
        "meHostName": "KLT1;ig-charging-68775f8668-n5gf2",
        "nccVersion": "SPS_23_5_R1",
        "RecordTimestamp": "08/09/2025 16:38:24",
        "localRecordSequenceNumber": "140254"
      },
      "recordExtensions": [
        {
          "recordProperty": "listOfSubscriptionID",
          "recordSubExtensions": [
            {
              "recordProperty": "subscriptionId",
              "recordElements": {
                "subscriptionIdType": "102",
                "subscriptionIdData": "imsi-636020101005561"
              }
            },
            {
              "recordProperty": "subscriptionId",
              "recordElements": {
                "subscriptionIdType": "1",
                "subscriptionIdData": "636020101005561"
              }
            },
            {
              "recordProperty": "subscriptionId",
              "recordElements": {
                "subscriptionIdType": "103",
                "subscriptionIdData": "msisdn-251700900449"
              }
            },
            {
              "recordProperty": "subscriptionId",
              "recordElements": {
                "subscriptionIdType": "0",
                "subscriptionIdData": "251700900449"
              }
            },
            {
              "recordProperty": "subscriptionId",
              "recordElements": {
                "subscriptionIdType": "101",
                "subscriptionIdData": "D_10435081"
              }
            }
          ]
        },
        {
          "recordProperty": "listOfMscc",
          "recordSubExtensions": [
            {
              "recordProperty": "mscc",
              "recordElements": {
                "usedUnitType": "TIME",
                "recordEventType": "IMS",
                "chargingType": "ONLINE_CHARGING",
                "firstDataStart": "08/09/2025 19:38:06+03:00",
                "lastDataUsage": "08/09/2025 19:38:24+03:00",
                "ratingGroup": "5",
                "subRecordEventType": "MOC",
                "timeUsage": "18",
                "resultCode": "2001",
                "recordEventResult": "00",
                "serviceIdentifier": "2",
                "usageType": "TIME",
                "localSequenceNumber": "1",
                "totalTimeConsumed": "0"
              },
              "recordSubExtensions": [
                {
                  "recordProperty": "deviceInfo",
                  "recordSubExtensions": [
                    {
                      "recordProperty": "subscriptionInfo",
                      "recordElements": {
                        "subscriptionId": "b1297ba2-9741-4e2d-9d76-43cad95af5d4",
                        "subscriptionState": "ACTIVE",
                        "bundleName": "ENTERPRISE_PREPAY_BASE_PLAN",
                        "bundleVersion": "5",
                        "accountID": "A_10435081",
                        "subscriptionStartDateTime": "08/09/2025 19:37:38+03:00",
                        "subscriptionEndDateTime": "08/09/2026 00:00:00+03:00",
                        "alternateId": "CRM:5f549872-4344-4cb7-9ade-c18134169d39:251700900449-CRM216z27sn_1755460149751-null-0-Self"
                      },
                      "recordSubExtensions": [
                        {
                          "recordProperty": "chargingServiceInfo",
                          "recordElements": {
                            "chargingServiceName": "TP_EBU_BASE_VOICE_V1",
                            "chargingServiceType": "TIME",
                            "chargingServicePriority": "10000",
                            "chargingServiceCategory": "DefaultCategory"
                          },
                          "recordSubExtensions": [
                            {
                              "recordProperty": "accountInfo",
                              "recordElements": {
                                "accountID": "A_10435081",
                                "accountType": "PRE_PAID",
                                "accountState": "ACTIVE",
                                "accountBalanceBefore": "387267.66666",
                                "accountBalanceAfter": "387267.66666",
                                "accountOveragelimit": "0.00000",
                                "accountBalanceCommitted": "0.00000",
                                "loanStateAfter": "INITIAL",
                                "rateId": "VR_0_50",
                                "taxationID": "Tax",
                                "taxRateApplied": "20.75000",
                                "committedTaxAmount": "0.00000",
                                "totalTaxAmount": "0.00000",
                                "tariffID": "TP_EBU_BASE_VOICE_V1_TP_BASE_VOICE_V1_fallbackRules0",
                                "secondaryCostCommitted": "0.00000"
                              }
                            }
                          ]
                        }
                      ]
                    }
                  ]
                }
              ]
            }
          ]
        }
      ]
    }
  }
}