{
  "header": {
    "recordLength": 1493
  },
  "payload": {
    "genericRecord": {
      "recordType": "OCSChargingRecord",
      "recordElements": {
        "prevMeName": "ig-charging-767679d6c8-78n5p",
        "causeForRecClosing": "1",
        "requestType": "UPDATE_REQUEST",
        "serviceContextId": "32251@3gpp.org",
        "sessionSequenceNumber": "1",
        "generationTimestamp": "02/09/2025 13:04:42+03:00",
        "resultCode": "5012",
        "sessionId": "edc-nk-cmg-cp01;2dc1af99;68b6c137;636020101005405-34501065",
        "deviceId": "D_10434355",
        "deviceName": "D_10434355",
        "deviceOwner": "U_10434355",
        "deviceOwnerName": "U_10434355",
        "ocsHost": "mdc1labnccs01-oam.safaricomlab.net",
        "deviceState": "ACTIVE",
        "devicePartitionId": "1",
        "deviceSiteId": "1",
        "recordOpeningTime": "02/09/2025 13:04:42+03:00",
        "recordClosureTime": "02/09/2025 13:04:42+03:00",
        "duration": "0",
        "recordSequenceNumber": "0",
        "recordId": "20250902130442_1c45a936-38cb-4312-baf5-f5d8803b964e",
        "meHostName": "KLT1;ig-charging-767679d6c8-78n5p",
        "nccVersion": "SPS_23_5_R1",
        "RecordTimestamp": "02/09/2025 10:04:42",
        "localRecordSequenceNumber": "122388"
      },
      "recordExtensions": [
        {
          "recordProperty": "listOfSubscriptionID",
          "recordSubExtensions": [
            {
              "recordProperty": "subscriptionId",
              "recordElements": {
                "subscriptionIdType": "1",
                "subscriptionIdData": "636020101005405"
              }
            },
            {
              "recordProperty": "subscriptionId",
              "recordElements": {
                "subscriptionIdType": "102",
                "subscriptionIdData": "imsi-636020101005405"
              }
            },
            {
              "recordProperty": "subscriptionId",
              "recordElements": {
                "subscriptionIdType": "103",
                "subscriptionIdData": "msisdn-251700990087"
              }
            },
            {
              "recordProperty": "subscriptionId",
              "recordElements": {
                "subscriptionIdType": "101",
                "subscriptionIdData": "D_10434355"
              }
            },
            {
              "recordProperty": "subscriptionId",
              "recordElements": {
                "subscriptionIdType": "0",
                "subscriptionIdData": "251700990087"
              }
            },
            {
              "recordProperty": "subscriptionId",
              "recordElements": {
                "subscriptionIdType": "3",
                "subscriptionIdData": "36020101005405@nai.epc.mnc002.mcc636.3gppnetwork.org"
              }
            }
          ]
        }
      ]
    }
  }
}